trytoncommunity_account_es_facturae-7.6.0.dist-info/licenses/LICENSE
trytond/modules/account_es_facturae/__init__.py
trytond/modules/account_es_facturae/account.py
trytond/modules/account_es_facturae/account.xml
trytond/modules/account_es_facturae/message.xml
trytond/modules/account_es_facturae/party.py
trytond/modules/account_es_facturae/party.xml
trytond/modules/account_es_facturae/tryton.cfg
trytond/modules/account_es_facturae/locale/ca.po
trytond/modules/account_es_facturae/locale/es.po
trytond/modules/account_es_facturae/tests/__init__.py
trytond/modules/account_es_facturae/tests/test_module.py
trytond/modules/account_es_facturae/view/export_facturae_result.xml
trytond/modules/account_es_facturae/view/export_facturae_start.xml
trytond/modules/account_es_facturae/view/invoice_facturae_form.xml
trytond/modules/account_es_facturae/view/invoice_facturae_list.xml
trytond/modules/account_es_facturae/view/party_form.xml
trytoncommunity_account_es_facturae-7.6.0.dist-info/METADATA
trytoncommunity_account_es_facturae-7.6.0.dist-info/WHEEL
trytoncommunity_account_es_facturae-7.6.0.dist-info/entry_points.txt
trytoncommunity_account_es_facturae-7.6.0.dist-info/top_level.txt
trytoncommunity_account_es_facturae-7.6.0.dist-info/RECORD
