Metadata-Version: 2.4
Name: trytoncommunity_account_es_facturae
Version: 7.6.0
Summary: Tryton module for generating facturae invoices
Home-page: https://www.kopen.es/
Download-URL: https://foss.heptapod.net/tryton-community/modules/edocument_es_facturae/-/releases
Author: KOPEN SOFTWARE
Author-email: info@kopen.es
License: GPL-3
Project-URL: Bug Tracker, https://foss.heptapod.net/tryton-community/modules/account_es_facturae/-/issues
Project-URL: Forum, https://www.tryton.org/forum
Project-URL: Source Code, https://foss.heptapod.net/tryton-community/modules/account_es_facturae
Keywords: tryton invoice facturae
Classifier: Development Status :: 5 - Production/Stable
Classifier: Environment :: Plugins
Classifier: Framework :: Tryton
Classifier: Intended Audience :: Developers
Classifier: Intended Audience :: Financial and Insurance Industry
Classifier: Intended Audience :: Legal Industry
Classifier: License :: OSI Approved :: GNU General Public License v3 or later (GPLv3+)
Classifier: Natural Language :: Catalan
Classifier: Natural Language :: English
Classifier: Natural Language :: Spanish
Classifier: Operating System :: OS Independent
Classifier: Programming Language :: Python :: 3
Classifier: Programming Language :: Python :: 3.9
Classifier: Programming Language :: Python :: 3.10
Classifier: Programming Language :: Python :: 3.11
Classifier: Programming Language :: Python :: 3.12
Classifier: Programming Language :: Python :: 3.13
Classifier: Programming Language :: Python :: Implementation :: CPython
Classifier: Topic :: Office/Business
Requires-Python: >=3.9
License-File: LICENSE
Requires-Dist: trytond_account_invoice<7.7,>=7.6
Requires-Dist: trytoncommunity_edocument_es_facturae<7.7,>=7.6
Requires-Dist: trytond_party<7.7,>=7.6
Requires-Dist: trytond<7.7,>=7.6
Provides-Extra: test
Dynamic: author
Dynamic: author-email
Dynamic: classifier
Dynamic: description
Dynamic: description-content-type
Dynamic: download-url
Dynamic: home-page
Dynamic: keywords
Dynamic: license
Dynamic: license-file
Dynamic: project-url
Dynamic: provides-extra
Dynamic: requires-dist
Dynamic: requires-python
Dynamic: summary
